systemd_socketserver.py
systemd_socketserver-1.0.dist-info/METADATA
systemd_socketserver-1.0.dist-info/WHEEL
systemd_socketserver-1.0.dist-info/top_level.txt
systemd_socketserver-1.0.dist-info/RECORD
