Metadata-Version: 2.1
Name: systemd-socketserver
Version: 1.0
Summary: Socket server implementation that works with systemd socket activation
Home-page: https://github.com/zegelin/python-systemd-socketserver
Author: Adam Zegelin
Author-email: adam@zegelin.com
License: UNKNOWN
Platform: UNKNOWN
Classifier: Programming Language :: Python :: 3
Classifier: Intended Audience :: Developers
Requires-Python: >=3
Requires-Dist: systemd-python
